agno_storage/__init__.py
agno_storage-1.0.dist-info/LICENSE
agno_storage-1.0.dist-info/METADATA
agno_storage-1.0.dist-info/WHEEL
agno_storage-1.0.dist-info/top_level.txt
agno_storage-1.0.dist-info/RECORD
