Metadata-Version: 2.1
Name: agno-storage
Version: 1.0
Summary: Cloud agnostic storage service
Home-page: https://github.com/apurvchaudhary/agnostic-storages
Author: Apurv Chaudhary
Author-email: apurv.sirohi@gmail.com
License: MIT
Platform: UNKNOWN
Classifier: Framework :: Django :: 2.0
Classifier: Framework :: Django :: 3.0
Classifier: Development Status :: 3 - Alpha
Classifier: Intended Audience :: Developers
Classifier: Topic :: Software Development :: Libraries
Classifier: Programming Language :: Python :: 3.6
Classifier: Programming Language :: Python :: 3.7
Classifier: Programming Language :: Python :: 3.8
Classifier: Programming Language :: Python :: 3.9
Classifier: Operating System :: OS Independent
Requires-Dist: boto3
Requires-Dist: azure-storage-file-datalake
Requires-Dist: django
